<annotation>
    <folder>image</folder>
    <filename>2002_08_05_big_img_3392.jpg</filename>
    <source>
        <database>Unknown</database>
    </source>
    <size>
        <width>450</width>
        <height>427</height>
        <depth>3</depth>
    </size>
    <segmented>0</segmented>
    <object>
        <name>Face</name>
        <pose>Unspecified</pose>
        <truncated>0</truncated>
        <difficult>0</difficult>
        <bndbox>
            <xmin>86</xmin>
            <ymin>38</ymin>
            <xmax>252</xmax>
            <ymax>264</ymax>
        </bndbox>
    </object>
    <object>
        <name>Face</name>
        <pose>Unspecified</pose>
        <truncated>0</truncated>
        <difficult>0</difficult>
        <bndbox>
            <xmin>258</xmin>
            <ymin>17</ymin>
            <xmax>361</xmax>
            <ymax>159</ymax>
        </bndbox>
    </object>
    <object>
        <name>Face</name>
        <pose>Unspecified</pose>
        <truncated>0</truncated>
        <difficult>0</difficult>
        <bndbox>
            <xmin>235</xmin>
            <ymin>68</ymin>
            <xmax>301</xmax>
            <ymax>169</ymax>
        </bndbox>
    </object>
    <object>
        <name>Face</name>
        <pose>Unspecified</pose>
        <truncated>0</truncated>
        <difficult>0</difficult>
        <bndbox>
            <xmin>0</xmin>
            <ymin>148</ymin>
            <xmax>51</xmax>
            <ymax>219</ymax>
        </bndbox>
    </object>
</annotation>