<annotation>
    <folder>image</folder>
    <filename>2002_09_01_big_img_16229.jpg</filename>
    <source>
        <database>Unknown</database>
    </source>
    <size>
        <width>393</width>
        <height>450</height>
        <depth>3</depth>
    </size>
    <segmented>0</segmented>
    <object>
        <name>Face</name>
        <pose>Unspecified</pose>
        <truncated>0</truncated>
        <difficult>0</difficult>
        <bndbox>
            <xmin>81</xmin>
            <ymin>30</ymin>
            <xmax>215</xmax>
            <ymax>240</ymax>
        </bndbox>
    </object>
    <object>
        <name>Face</name>
        <pose>Unspecified</pose>
        <truncated>0</truncated>
        <difficult>0</difficult>
        <bndbox>
            <xmin>206</xmin>
            <ymin>127</ymin>
            <xmax>322</xmax>
            <ymax>282</ymax>
        </bndbox>
    </object>
</annotation>