<annotation>
    <folder>image</folder>
    <filename>2002_07_28_big_img_465.jpg</filename>
    <source>
        <database>Unknown</database>
    </source>
    <size>
        <width>450</width>
        <height>333</height>
        <depth>3</depth>
    </size>
    <segmented>0</segmented>
    <object>
        <name>Face</name>
        <pose>Unspecified</pose>
        <truncated>0</truncated>
        <difficult>0</difficult>
        <bndbox>
            <xmin>74</xmin>
            <ymin>100</ymin>
            <xmax>154</xmax>
            <ymax>222</ymax>
        </bndbox>
    </object>
    <object>
        <name>Face</name>
        <pose>Unspecified</pose>
        <truncated>0</truncated>
        <difficult>0</difficult>
        <bndbox>
            <xmin>226</xmin>
            <ymin>38</ymin>
            <xmax>302</xmax>
            <ymax>147</ymax>
        </bndbox>
    </object>
    <object>
        <name>Face</name>
        <pose>Unspecified</pose>
        <truncated>0</truncated>
        <difficult>0</difficult>
        <bndbox>
            <xmin>361</xmin>
            <ymin>80</ymin>
            <xmax>408</xmax>
            <ymax>143</ymax>
        </bndbox>
    </object>
</annotation>