<annotation>
    <folder>image</folder>
    <filename>2002_07_22_big_img_342.jpg</filename>
    <source>
        <database>Unknown</database>
    </source>
    <size>
        <width>450</width>
        <height>316</height>
        <depth>3</depth>
    </size>
    <segmented>0</segmented>
    <object>
        <name>Face</name>
        <pose>Unspecified</pose>
        <truncated>0</truncated>
        <difficult>0</difficult>
        <bndbox>
            <xmin>29</xmin>
            <ymin>19</ymin>
            <xmax>102</xmax>
            <ymax>133</ymax>
        </bndbox>
    </object>
    <object>
        <name>Face</name>
        <pose>Unspecified</pose>
        <truncated>0</truncated>
        <difficult>0</difficult>
        <bndbox>
            <xmin>99</xmin>
            <ymin>54</ymin>
            <xmax>170</xmax>
            <ymax>152</ymax>
        </bndbox>
    </object>
    <object>
        <name>Face</name>
        <pose>Unspecified</pose>
        <truncated>0</truncated>
        <difficult>0</difficult>
        <bndbox>
            <xmin>284</xmin>
            <ymin>48</ymin>
            <xmax>358</xmax>
            <ymax>164</ymax>
        </bndbox>
    </object>
    <object>
        <name>Face</name>
        <pose>Unspecified</pose>
        <truncated>0</truncated>
        <difficult>0</difficult>
        <bndbox>
            <xmin>338</xmin>
            <ymin>90</ymin>
            <xmax>413</xmax>
            <ymax>192</ymax>
        </bndbox>
    </object>
    <object>
        <name>Face</name>
        <pose>Unspecified</pose>
        <truncated>0</truncated>
        <difficult>0</difficult>
        <bndbox>
            <xmin>162</xmin>
            <ymin>34</ymin>
            <xmax>240</xmax>
            <ymax>156</ymax>
        </bndbox>
    </object>
    <object>
        <name>Face</name>
        <pose>Unspecified</pose>
        <truncated>0</truncated>
        <difficult>0</difficult>
        <bndbox>
            <xmin>245</xmin>
            <ymin>118</ymin>
            <xmax>306</xmax>
            <ymax>200</ymax>
        </bndbox>
    </object>
</annotation>