<annotation>
    <folder>image</folder>
    <filename>2003_01_14_big_img_925.jpg</filename>
    <source>
        <database>Unknown</database>
    </source>
    <size>
        <width>337</width>
        <height>450</height>
        <depth>3</depth>
    </size>
    <segmented>0</segmented>
    <object>
        <name>Face</name>
        <pose>Unspecified</pose>
        <truncated>0</truncated>
        <difficult>0</difficult>
        <bndbox>
            <xmin>85</xmin>
            <ymin>43</ymin>
            <xmax>299</xmax>
            <ymax>371</ymax>
        </bndbox>
    </object>
    <object>
        <name>Face</name>
        <pose>Unspecified</pose>
        <truncated>0</truncated>
        <difficult>0</difficult>
        <bndbox>
            <xmin>1</xmin>
            <ymin>68</ymin>
            <xmax>75</xmax>
            <ymax>177</ymax>
        </bndbox>
    </object>
    <object>
        <name>Face</name>
        <pose>Unspecified</pose>
        <truncated>0</truncated>
        <difficult>0</difficult>
        <bndbox>
            <xmin>17</xmin>
            <ymin>198</ymin>
            <xmax>96</xmax>
            <ymax>314</ymax>
        </bndbox>
    </object>
    <object>
        <name>Face</name>
        <pose>Unspecified</pose>
        <truncated>0</truncated>
        <difficult>0</difficult>
        <bndbox>
            <xmin>226</xmin>
            <ymin>74</ymin>
            <xmax>337</xmax>
            <ymax>237</ymax>
        </bndbox>
    </object>
</annotation>